avalips/config_parse.py
avalips-0.1.dist-info/METADATA
avalips-0.1.dist-info/WHEEL
avalips-0.1.dist-info/top_level.txt
avalips-0.1.dist-info/RECORD
